led_calibration_plugin/__init__.py
led_calibration_plugin/calibrated_light_dark_cycle.py
led_calibration_plugin/led_calibration.py
led_calibration_plugin/test_led_calibration.py
led_calibration_plugin/ui/contrib/automations/led/calibrated_light_dark_cycle.yaml
led_calibration_plugin-2.0.0.dist-info/LICENSE.txt
led_calibration_plugin-2.0.0.dist-info/METADATA
led_calibration_plugin-2.0.0.dist-info/WHEEL
led_calibration_plugin-2.0.0.dist-info/entry_points.txt
led_calibration_plugin-2.0.0.dist-info/top_level.txt
led_calibration_plugin-2.0.0.dist-info/RECORD
