Metadata-Version: 2.2
Name: led-calibration-plugin
Version: 2.0.0
Summary: Calibrate your LEDs using an external light probe.
Home-page: https://github.com/pioreactor/pioreactor-led-calibration-plugin
Author: Kelly Tran, Pioreactor
Author-email: cam@pioreactor.com
License: MIT
License-File: LICENSE.txt
Dynamic: author
Dynamic: author-email
Dynamic: description
Dynamic: description-content-type
Dynamic: home-page
Dynamic: license
Dynamic: summary
